<?xml version="1.0" encoding="UTF-8"?>
<objects serializationModel="Studio.01.10.00">
    <object class="AudioFile" id="{6985a3a2-5524-4c62-9a86-4186fef6c979}">
        <property name="assetPath">
            <value>Footsteps_Gravel_3.wav</value>
        </property>
        <property name="frequencyInKHz">
            <value>44.0999985</value>
        </property>
        <property name="channelCount">
            <value>2</value>
        </property>
        <property name="length">
            <value>0.53866213151927433</value>
        </property>
        <relationship name="masterAssetFolder">
            <destination>{7d733894-a03d-4ab5-a4b9-50ee91587498}</destination>
        </relationship>
    </object>
</objects>
